dolomite_base/read_atomic_vector.py
dolomite_base/alt_read_object.py
dolomite_base/save_atomic_vector.py
dolomite_base/write_vector_to_hdf5.py
dolomite_base/choose_missing_placeholder.py
dolomite_base/_utils_misc.py
dolomite_base/read_simple_list.py
dolomite_base/alt_save_object.py
dolomite_base/__init__.py
dolomite_base/save_object_file.py
dolomite_base/save_data_frame.py
dolomite_base/_utils_string.py
dolomite_base/read_object_file.py
dolomite_base/save_simple_list.py
dolomite_base/validate_directory.py
dolomite_base/save_object.py
dolomite_base/read_object.py
dolomite_base/lib_dolomite_base.cpython-311-darwin.so
dolomite_base/validate_object.py
dolomite_base/read_string_factor.py
dolomite_base/_utils_factor.py
dolomite_base/load_vector_from_hdf5.py
dolomite_base/save_string_factor.py
dolomite_base/list_objects.py
dolomite_base/read_data_frame.py
dolomite_base-0.5.1.dist-info/RECORD
dolomite_base-0.5.1.dist-info/WHEEL
dolomite_base-0.5.1.dist-info/top_level.txt
dolomite_base-0.5.1.dist-info/METADATA
dolomite_base-0.5.1.dist-info/licenses/LICENSE.txt
