Metadata-Version: 2.4
Name: dolomite-base
Version: 0.5.1
Summary: Save and load Bioconductor objects in Python
Home-page: https://github.com/ArtifactDB/dolomite-base
Author: Aaron Lun
Author-email: infinite.monkeys.with.keyboards@gmail.com
License: MIT
Project-URL: Documentation, https://github.com/ArtifactDB/dolomite-base
Project-URL: Source, https://github.com/ArtifactDB/dolomite-base
Platform: any
Classifier: Development Status :: 4 - Beta
Classifier: Programming Language :: Python
Requires-Python: >=3.9
License-File: LICENSE.txt
Requires-Dist: importlib-metadata; python_version < "3.8"
Requires-Dist: biocutils
Requires-Dist: biocframe>=0.6.0
Requires-Dist: numpy
Requires-Dist: h5py
Provides-Extra: testing
Requires-Dist: setuptools; extra == "testing"
Requires-Dist: pytest; extra == "testing"
Requires-Dist: pytest-cov; extra == "testing"
Dynamic: license-file
